cartoonizer/__init__.py
cartoonizer/cartoon_effect.py
cartoonizer/color_quantization.py
cartoonizer/edge_detection.py
cartoonizer/preprocessing.py
cartoonizer_thellmike-0.1.1.dist-info/LICENSE
cartoonizer_thellmike-0.1.1.dist-info/METADATA
cartoonizer_thellmike-0.1.1.dist-info/WHEEL
cartoonizer_thellmike-0.1.1.dist-info/top_level.txt
cartoonizer_thellmike-0.1.1.dist-info/RECORD
