Metadata-Version: 2.1
Name: cartoonizer-thellmike
Version: 0.1.1
Summary: A library for converting normal pictures to cartoon-like images
Home-page: https://github.com/thelllmike/cartoonizer.git
Author: Sachin Harshitha
Author-email: sachinharshitha971@gmail.com
Classifier: Programming Language :: Python :: 3
Classifier: License :: OSI Approved :: MIT License
Classifier: Operating System :: OS Independent
Requires-Python: >=3.6
License-File: LICENSE
Requires-Dist: Pillow
Requires-Dist: numpy
Requires-Dist: opencv-python
